{"index": {"version":"2.2.0","fields":["description","excerpt","heading","tags","title"],"fieldVectors":[["description/2",[0,0.557,1,0.526,2,0.741,3,1.01]],["excerpt/2",[0,0.466,1,0.44,2,0.619,4,1.6,5,0.843,6,0.619,7,0.843,8,0.619,9,1.6,10,1.144,11,1.6,12,1.6,13,0.44,14,1.6,15,1.6,16,1.6]],["heading/2",[0,0.467,1,0.441,2,0.621,5,0.846,6,0.621,7,0.846,17,1.604,18,0.163,19,0.291]],["tags/2",[3,1.206]],["title/2",[0,0.469,1,0.444,2,0.624,5,0.851,6,0.624,7,0.851,18,0.164,19,0.293,20,1.614,21,1.614]],["description/3",[0,0.471,22,0.052,23,0.294,24,0.853,25,0.853,26,0.445]],["excerpt/3",[0,0.466,8,0.619,10,1.144,18,0.163,23,0.291,26,0.44,27,1.144,28,1.6,29,1.6,30,1.6,31,1.6,32,1.6,33,1.6,34,1.6,35,1.144,36,1.6]],["heading/3",[0,0.554,22,0.061,23,0.346,24,1.003,25,1.003,26,0.523]],["tags/3",[23,0.333,26,0.505]],["title/3",[0,0.578,22,0.063,23,0.361,24,1.046,25,1.046,26,0.546]],["description/4",[0,0.471,37,0.626,38,0.445,39,0.853,40,0.853,41,0.853]],["excerpt/4",[0,0.48,37,0.638,38,0.639,42,1.649,43,1.179,44,1.649,45,1.649,46,1.179,47,1.179,48,1.649,49,1.649,50,1.649,51,1.179,52,1.649]],["heading/4",[0,0.554,37,0.736,38,0.523,39,1.003,40,1.003,41,1.003]],["tags/4",[38,0.421,46,1.096,47,1.096]],["title/4",[0,0.578,37,0.768,38,0.546,39,1.046,40,1.046,41,1.046]],["description/5",[53,1.508,54,1.508,55,0.816]],["excerpt/5",[0,0.66,55,0.878,56,1.623,57,1.623,58,1.623,59,1.623]],["heading/5",[0,0.554,55,0.736,56,1.36,57,1.36,58,1.36,59,1.36]],["tags/5",[60,0.968,61,1.836]],["title/5",[0,0.493,53,1.21,54,1.21,55,0.655,62,1.693,63,1.693,64,1.21,65,1.693,66,0.465]],["description/6",[0,0.471,13,0.445,18,0.165,19,0.294,67,0.626,68,0.626]],["excerpt/6",[0,0.44,1,0.6,6,0.584,8,0.584,13,0.415,27,1.08,35,1.08,43,1.08,67,0.584,68,0.584,69,1.08,70,1.511,71,0.274,72,1.511,73,1.511,74,1.511,75,1.511]],["heading/6",[0,0.554,13,0.523,18,0.194,19,0.346,67,0.736,68,0.736]],["tags/6",[3,1.206]],["title/6",[0,0.578,13,0.546,18,0.202,19,0.361,67,0.768,68,0.768]],["description/7",[66,0.645,76,0.645]],["excerpt/7",[0,0.587,8,0.78,22,0.064,66,0.554,71,0.366,76,0.554,77,2.017,78,2.017,79,2.017]],["heading/7",[66,0.558,71,0.368,76,0.558,80,2.029,81,2.029]],["tags/7",[60,0.808,69,1.096,76,0.421]],["title/7",[0,0.518,18,0.181,19,0.323,66,0.489,76,0.489,82,1.78,83,1.78,84,1.78]],["description/8",[0,0.51,85,1.754,86,0.925,87,0.925,88,0.925]],["excerpt/8",[0,0.587,22,0.064,23,0.366,71,0.366,89,2.017,90,2.017,91,2.017,92,1.063,93,2.017]],["heading/8",[0,0.403,71,0.252,86,0.731,87,0.731,88,0.731,92,1.081,94,0.991,95,0.991,96,0.991,97,0.991,98,0.991]],["tags/8",[60,1.206]],["title/8",[0,0.429,71,0.268,86,0.778,87,0.778,88,0.778,92,1.132,94,1.055,95,1.055,96,1.055,97,1.055,98,1.055]],["description/9",[0,0.471,22,0.052,99,0.445,100,0.445,101,0.445,102,0.853]],["excerpt/9",[51,1.39,64,1.39,99,0.534,100,0.534,101,0.534,103,1.944,104,1.944,105,1.944,106,1.944,107,1.39]],["heading/9",[0,0.554,22,0.061,99,0.523,100,0.523,101,0.523,102,1.003]],["tags/9",[99,0.362,100,0.362,101,0.362,107,0.941]],["title/9",[0,0.578,22,0.063,99,0.546,100,0.546,101,0.546,102,1.046]]],"invertedIndex":[["",{"_index":17,"description":{},"excerpt":{},"heading":{"2":{}},"tags":{},"title":{}}],["25,000",{"_index":68,"description":{"6":{}},"excerpt":{"6":{}},"heading":{"6":{}},"tags":{},"title":{"6":{}}}],["4th",{"_index":95,"description":{},"excerpt":{},"heading":{"8":{}},"tags":{},"title":{"8":{}}}],["5",{"_index":5,"description":{},"excerpt":{"2":{}},"heading":{"2":{}},"tags":{},"title":{"2":{}}}],["50,000",{"_index":63,"description":{},"excerpt":{},"heading":{},"tags":{},"title":{"5":{}}}],["500",{"_index":83,"description":{},"excerpt":{},"heading":{},"tags":{},"title":{"7":{}}}],["5000",{"_index":14,"description":{},"excerpt":{"2":{}},"heading":{},"tags":{},"title":{}}],["5k",{"_index":21,"description":{},"excerpt":{},"heading":{},"tags":{},"title":{"2":{}}}],["a",{"_index":13,"description":{"6":{}},"excerpt":{"2":{},"6":{}},"heading":{"6":{}},"tags":{},"title":{"6":{}}}],["al",{"_index":87,"description":{"8":{}},"excerpt":{},"heading":{"8":{}},"tags":{},"title":{"8":{}}}],["alia",{"_index":86,"description":{"8":{}},"excerpt":{},"heading":{"8":{}},"tags":{},"title":{"8":{}}}],["amaz",{"_index":38,"description":{"4":{}},"excerpt":{"4":{}},"heading":{"4":{}},"tags":{"4":{}},"title":{"4":{}}}],["annual",{"_index":96,"description":{},"excerpt":{},"heading":{"8":{}},"tags":{},"title":{"8":{}}}],["around",{"_index":40,"description":{"4":{}},"excerpt":{},"heading":{"4":{}},"tags":{},"title":{"4":{}}}],["art",{"_index":23,"description":{"3":{}},"excerpt":{"3":{},"8":{}},"heading":{"3":{}},"tags":{"3":{}},"title":{"3":{}}}],["artist",{"_index":98,"description":{},"excerpt":{},"heading":{"8":{}},"tags":{},"title":{"8":{}}}],["away",{"_index":19,"description":{"6":{}},"excerpt":{},"heading":{"2":{},"6":{}},"tags":{},"title":{"2":{},"6":{},"7":{}}}],["bakeri",{"_index":31,"description":{},"excerpt":{"3":{}},"heading":{},"tags":{},"title":{}}],["boss",{"_index":102,"description":{"9":{}},"excerpt":{},"heading":{"9":{}},"tags":{},"title":{"9":{}}}],["brewti",{"_index":81,"description":{},"excerpt":{},"heading":{"7":{}},"tags":{},"title":{}}],["burger",{"_index":7,"description":{},"excerpt":{"2":{}},"heading":{"2":{}},"tags":{},"title":{"2":{}}}],["campaign",{"_index":48,"description":{},"excerpt":{"4":{}},"heading":{},"tags":{},"title":{}}],["cash",{"_index":15,"description":{},"excerpt":{"2":{}},"heading":{},"tags":{},"title":{}}],["celebr",{"_index":22,"description":{"3":{},"9":{}},"excerpt":{"7":{},"8":{}},"heading":{"3":{},"9":{}},"tags":{},"title":{"3":{},"9":{}}}],["chanc",{"_index":33,"description":{},"excerpt":{"3":{}},"heading":{},"tags":{},"title":{}}],["cinco",{"_index":99,"description":{"9":{}},"excerpt":{"9":{}},"heading":{"9":{}},"tags":{"9":{}},"title":{"9":{}}}],["coffe",{"_index":76,"description":{"7":{}},"excerpt":{"7":{}},"heading":{"7":{}},"tags":{"7":{}},"title":{"7":{}}}],["coincid",{"_index":42,"description":{},"excerpt":{"4":{}},"heading":{},"tags":{},"title":{}}],["come",{"_index":104,"description":{},"excerpt":{"9":{}},"heading":{},"tags":{},"title":{}}],["competit",{"_index":3,"description":{"2":{}},"excerpt":{},"heading":{},"tags":{"2":{},"6":{}},"title":{}}],["cooki",{"_index":26,"description":{"3":{}},"excerpt":{"3":{}},"heading":{"3":{}},"tags":{"3":{}},"title":{"3":{}}}],["costa",{"_index":82,"description":{},"excerpt":{},"heading":{},"tags":{},"title":{"7":{}}}],["creat",{"_index":89,"description":{},"excerpt":{"8":{}},"heading":{},"tags":{},"title":{}}],["creation",{"_index":50,"description":{},"excerpt":{"4":{}},"heading":{},"tags":{},"title":{}}],["cup",{"_index":84,"description":{},"excerpt":{},"heading":{},"tags":{},"title":{"7":{}}}],["custom",{"_index":32,"description":{},"excerpt":{"3":{}},"heading":{},"tags":{},"title":{}}],["day",{"_index":71,"description":{},"excerpt":{"6":{},"7":{},"8":{}},"heading":{"7":{},"8":{}},"tags":{},"title":{"8":{}}}],["de",{"_index":100,"description":{"9":{}},"excerpt":{"9":{}},"heading":{"9":{}},"tags":{"9":{}},"title":{"9":{}}}],["deliveroo",{"_index":0,"description":{"2":{},"3":{},"4":{},"6":{},"8":{},"9":{}},"excerpt":{"2":{},"3":{},"4":{},"5":{},"6":{},"7":{},"8":{}},"heading":{"2":{},"3":{},"4":{},"5":{},"6":{},"8":{},"9":{}},"tags":{},"title":{"2":{},"3":{},"4":{},"5":{},"6":{},"7":{},"8":{},"9":{}}}],["dish",{"_index":39,"description":{"4":{}},"excerpt":{},"heading":{"4":{}},"tags":{},"title":{"4":{}}}],["distribut",{"_index":62,"description":{},"excerpt":{},"heading":{},"tags":{},"title":{"5":{}}}],["dubai",{"_index":11,"description":{},"excerpt":{"2":{}},"heading":{},"tags":{},"title":{}}],["e",{"_index":30,"description":{},"excerpt":{"3":{}},"heading":{},"tags":{},"title":{}}],["each",{"_index":12,"description":{},"excerpt":{"2":{}},"heading":{},"tags":{},"title":{}}],["eat",{"_index":46,"description":{},"excerpt":{"4":{}},"heading":{},"tags":{"4":{}},"title":{}}],["eco",{"_index":53,"description":{"5":{}},"excerpt":{},"heading":{},"tags":{},"title":{"5":{}}}],["emirati",{"_index":92,"description":{},"excerpt":{"8":{}},"heading":{"8":{}},"tags":{},"title":{"8":{}}}],["environ",{"_index":61,"description":{},"excerpt":{},"heading":{},"tags":{"5":{}},"title":{}}],["fiesta",{"_index":103,"description":{},"excerpt":{"9":{}},"heading":{},"tags":{},"title":{}}],["find",{"_index":75,"description":{},"excerpt":{"6":{}},"heading":{},"tags":{},"title":{}}],["five",{"_index":1,"description":{"2":{}},"excerpt":{"2":{},"6":{}},"heading":{"2":{}},"tags":{},"title":{"2":{}}}],["food",{"_index":60,"description":{},"excerpt":{},"heading":{},"tags":{"5":{},"7":{},"8":{}},"title":{}}],["foodi",{"_index":49,"description":{},"excerpt":{"4":{}},"heading":{},"tags":{},"title":{}}],["free",{"_index":66,"description":{"7":{}},"excerpt":{"7":{}},"heading":{"7":{}},"tags":{},"title":{"5":{},"7":{}}}],["friend",{"_index":105,"description":{},"excerpt":{"9":{}},"heading":{},"tags":{},"title":{}}],["friendli",{"_index":54,"description":{"5":{}},"excerpt":{},"heading":{},"tags":{},"title":{"5":{}}}],["give",{"_index":18,"description":{"6":{}},"excerpt":{"3":{}},"heading":{"2":{},"6":{}},"tags":{},"title":{"2":{},"6":{},"7":{}}}],["giveaway",{"_index":69,"description":{},"excerpt":{"6":{}},"heading":{},"tags":{"7":{}},"title":{}}],["golden",{"_index":6,"description":{},"excerpt":{"2":{},"6":{}},"heading":{"2":{}},"tags":{},"title":{"2":{}}}],["grab",{"_index":9,"description":{},"excerpt":{"2":{}},"heading":{},"tags":{},"title":{}}],["guy",{"_index":2,"description":{"2":{}},"excerpt":{"2":{}},"heading":{"2":{}},"tags":{},"title":{"2":{}}}],["homegrown",{"_index":29,"description":{},"excerpt":{"3":{}},"heading":{},"tags":{},"title":{}}],["honour",{"_index":94,"description":{},"excerpt":{},"heading":{"8":{}},"tags":{},"title":{"8":{}}}],["host",{"_index":106,"description":{},"excerpt":{"9":{}},"heading":{},"tags":{},"title":{}}],["intern",{"_index":77,"description":{},"excerpt":{"7":{}},"heading":{},"tags":{},"title":{}}],["it'",{"_index":44,"description":{},"excerpt":{"4":{}},"heading":{},"tags":{},"title":{}}],["it’",{"_index":80,"description":{},"excerpt":{},"heading":{"7":{}},"tags":{},"title":{}}],["launch",{"_index":43,"description":{},"excerpt":{"4":{},"6":{}},"heading":{},"tags":{},"title":{}}],["lucki",{"_index":72,"description":{},"excerpt":{"6":{}},"heading":{},"tags":{},"title":{}}],["mayo",{"_index":101,"description":{"9":{}},"excerpt":{"9":{}},"heading":{"9":{}},"tags":{"9":{}},"title":{"9":{}}}],["mexican",{"_index":107,"description":{},"excerpt":{"9":{}},"heading":{},"tags":{"9":{}},"title":{}}],["month",{"_index":24,"description":{"3":{}},"excerpt":{},"heading":{"3":{}},"tags":{},"title":{"3":{}}}],["more",{"_index":47,"description":{},"excerpt":{"4":{}},"heading":{},"tags":{"4":{}},"title":{}}],["need",{"_index":74,"description":{},"excerpt":{"6":{}},"heading":{},"tags":{},"title":{}}],["new",{"_index":45,"description":{},"excerpt":{"4":{}},"heading":{},"tags":{},"title":{}}],["on",{"_index":58,"description":{},"excerpt":{"5":{}},"heading":{"5":{}},"tags":{},"title":{}}],["order",{"_index":51,"description":{},"excerpt":{"4":{},"9":{}},"heading":{},"tags":{},"title":{}}],["over",{"_index":70,"description":{},"excerpt":{"6":{}},"heading":{},"tags":{},"title":{}}],["paint",{"_index":34,"description":{},"excerpt":{"3":{}},"heading":{},"tags":{},"title":{}}],["paintabl",{"_index":25,"description":{"3":{}},"excerpt":{},"heading":{"3":{}},"tags":{},"title":{"3":{}}}],["partner",{"_index":65,"description":{},"excerpt":{},"heading":{},"tags":{},"title":{"5":{}}}],["partnership",{"_index":85,"description":{"8":{}},"excerpt":{},"heading":{},"tags":{},"title":{}}],["piec",{"_index":91,"description":{},"excerpt":{"8":{}},"heading":{},"tags":{},"title":{}}],["planet",{"_index":57,"description":{},"excerpt":{"5":{}},"heading":{"5":{}},"tags":{},"title":{}}],["platform",{"_index":52,"description":{},"excerpt":{"4":{}},"heading":{},"tags":{},"title":{}}],["prize",{"_index":16,"description":{},"excerpt":{"2":{}},"heading":{},"tags":{},"title":{}}],["restaur",{"_index":64,"description":{},"excerpt":{"9":{}},"heading":{},"tags":{},"title":{"5":{}}}],["reveal",{"_index":37,"description":{"4":{}},"excerpt":{"4":{}},"heading":{"4":{}},"tags":{},"title":{"4":{}}}],["roo",{"_index":35,"description":{},"excerpt":{"3":{},"6":{}},"heading":{},"tags":{},"title":{}}],["save",{"_index":56,"description":{},"excerpt":{"5":{}},"heading":{"5":{}},"tags":{},"title":{}}],["shamsi",{"_index":88,"description":{"8":{}},"excerpt":{},"heading":{"8":{}},"tags":{},"title":{"8":{}}}],["shape",{"_index":36,"description":{},"excerpt":{"3":{}},"heading":{},"tags":{},"title":{}}],["special",{"_index":90,"description":{},"excerpt":{"8":{}},"heading":{},"tags":{},"title":{}}],["straw",{"_index":55,"description":{"5":{}},"excerpt":{"5":{}},"heading":{"5":{}},"tags":{},"title":{"5":{}}}],["sugarmoo",{"_index":28,"description":{},"excerpt":{"3":{}},"heading":{},"tags":{},"title":{}}],["taqado",{"_index":67,"description":{"6":{}},"excerpt":{"6":{}},"heading":{"6":{}},"tags":{},"title":{"6":{}}}],["team",{"_index":27,"description":{},"excerpt":{"3":{},"6":{}},"heading":{},"tags":{},"title":{}}],["thank",{"_index":4,"description":{},"excerpt":{"2":{}},"heading":{},"tags":{},"title":{}}],["time",{"_index":59,"description":{},"excerpt":{"5":{}},"heading":{"5":{}},"tags":{},"title":{}}],["ultim",{"_index":78,"description":{},"excerpt":{"7":{}},"heading":{},"tags":{},"title":{}}],["up",{"_index":8,"description":{},"excerpt":{"2":{},"3":{},"6":{},"7":{}},"heading":{},"tags":{},"title":{}}],["wake",{"_index":79,"description":{},"excerpt":{"7":{}},"heading":{},"tags":{},"title":{}}],["week",{"_index":10,"description":{},"excerpt":{"2":{},"3":{}},"heading":{},"tags":{},"title":{}}],["winner",{"_index":73,"description":{},"excerpt":{"6":{}},"heading":{},"tags":{},"title":{}}],["women'",{"_index":93,"description":{},"excerpt":{"8":{}},"heading":{},"tags":{},"title":{}}],["women’",{"_index":97,"description":{},"excerpt":{},"heading":{"8":{}},"tags":{},"title":{"8":{}}}],["world",{"_index":41,"description":{"4":{}},"excerpt":{},"heading":{"4":{}},"tags":{},"title":{"4":{}}}],["worth",{"_index":20,"description":{},"excerpt":{},"heading":{},"tags":{},"title":{"2":{}}}]],"pipeline":["stemmer"]}, "docs": {"2":{"excerpt":"Thanks to Deliveroo and Five Guys, 5 golden burgers are up for grabs this week in Dubai and they each have a AED 5000 cash prize!","heading":"Deliveroo & Five Guys are giving away 5 golden burgers","image":"/assets/images/blogs/ae.deliveroo.news/en/news/1bFBj1yydMBM-t3zl6bm1U89uuG9HzQMmnTBXaK_UyyE/h_consum-2407_uk_five-guys_promotion_pr_1200x628_still__1_.jpg?v=1.01","url":"/news/deliveroo-and-fiveguys-goldenburger.html"},"3":{"excerpt":"This Art Week, Deliveroo is teaming up with SugarMoo, the homegrown e-bakery, to give customers the chance to paint their own Roo-shaped cookies","heading":"Deliveroo celebrates art month with paintable cookies","image":"/assets/images/blogs/ae.deliveroo.news/en/news/1RpHO1dV8-VWm1XPOmW-O8SLEHFBMYgu_piyy7hnNmsc/h_pistachio-cake-750x400.jpg?v=1.01","url":"/news/deliveroo-celebrates-art-month.html"},"4":{"excerpt":"To coincide with the launch of it's new 'Eat More Amazing' campaign, Deliveroo reveals some of the most amazing foodie creations you can order on the platform","heading":"Deliveroo reveals most amazing dishes around the world","image":"/assets/images/blogs/ae.deliveroo.news/en/news/1NeWD_zybwXiVJyajmVQqdp4fw2shAeB3NFaykjkmxJY/h_h_header_resize-1.jpg?v=1.01","url":"/news/most-amazing-dishes-around-the-world.html"},"5":{"excerpt":"Deliveroo is saving the planet one straw at a time","heading":"Deliveroo is saving the planet one straw at a time","image":"/assets/images/blogs/ae.deliveroo.news/en/news/1oFxtXmJpF6az_pBZkDICla9td01Nq7ymmubjSYFNiLU/h_image1.jpg?v=1.01","url":"/news/deliveroo-eco-friendly-straws.html"},"6":{"excerpt":"Deliveroo is teaming up with Taqado to launch a AED 25,000 giveaway over five days to five lucky winners. All you need to do is find the Golden Roo","heading":"Deliveroo and Taqado are giving away AED 25,000!","image":"/assets/images/blogs/ae.deliveroo.news/en/news/1e_A4w-ynilCL6trFgwNYTDC3YL6sjx0vlNgrG0kgkxs/h_h_pasted_image_0.jpg?v=1.01","url":"/news/deliveroo-and-taqado-giveaway.html"},"7":{"excerpt":"Deliveroo celebrates International Coffee Day with the ultimate free wake up","heading":"It’s a Brewtiful Day for Free Coffee","image":"/assets/images/blogs/ae.deliveroo.news/en/news/11t842I91_Y41qaFjCVbX5iRIK3vpOsSRkPgAVi4n8Lg/h_pasted_image_0.jpg?v=1.01","url":"/news/deliveroo-coffee.html"},"8":{"excerpt":"Deliveroo creates a special piece of art to celebrate Emirati Women's Day","heading":"Deliveroo honours the 4th annual Emirati Women’s Day with Emirati Artist, Alia Al Shamsi","image":"/assets/images/blogs/ae.deliveroo.news/en/news/1Sk9GCJXH8XFOu3oCfL5vH99YHSYrqK0zHEMv4-j3yaI/h_pasted_image_0.jpg?v=1.01","url":"/news/deliveroo-emirati-womens-day.html"},"9":{"excerpt":"Let the fiesta come to you and your friends by ordering from a host of Mexican restaurants this Cinco de Mayo","heading":"Celebrate Cinco de Mayo like a boss with Deliveroo ","image":"/assets/images/blogs/ae.deliveroo.news/en/news/1J4bTBSBfChx14UpziHxkmy13HnlrVuzfFsYp24ui4hM/h_paris_catrina_guacamole1.1.jpg?v=1.01","url":"/news/celebrate-cinco-de-mayo-with-deliveroo.html"}}}